mpy_google/__init__.py
mpy_google/module1.py
mpy_google-0.0.0.1.dist-info/METADATA
mpy_google-0.0.0.1.dist-info/WHEEL
mpy_google-0.0.0.1.dist-info/top_level.txt
mpy_google-0.0.0.1.dist-info/RECORD
