Metadata-Version: 2.1
Name: mpy-google
Version: 0.0.0.1
Summary: google API for python
Home-page: UNKNOWN
Author: Moon Jung Sam
Author-email: monble@snu.ac.kr
License: MIT
Platform: UNKNOWN
Requires-Python: >=3
